{
    "qa_multi_document_information_integration": [
        {
            "问题类型": "多文档信息整合问题",
            "问题": "根据霜叶市第一人民医院和流水市人民医院的住院病历，喻某某和安某某的职业分别是什么？",
            "ref": [
                {
                    "医院_病人名": "霜叶市第一人民医院_喻某某",
                    "content": [
                        "职业：教师",
                        "职业为教师，工作压力适中。"
                    ]
                },
                {
                    "医院_病人名": "流水市人民医院_安某某",
                    "content": [
                        "姓名：安某某      性别：女      年龄：99岁      民族：汉族      婚姻状况：丧偶      职业：退休教师      住址：流水市茉莉街62号",
                        "职业及工作条件：退休教师，工作压力小，工作环境良好。"
                    ]
                }
            ],
            "答案": "根据霜叶市第一人民医院的住院病历，喻某某的职业是教师；根据流水市人民医院的住院病历，安某某的职业是退休教师。"
        },
        {
            "问题类型": "多文档信息整合问题",
            "问题": "根据霜叶市第一人民医院和流水市人民医院的住院病历，喻某某和安某某的住址分别是什么？",
            "ref": [
                {
                    "医院_病人名": "霜叶市第一人民医院_喻某某",
                    "content": [
                        "住址：霜叶市雨燕街84号"
                    ]
                },
                {
                    "医院_病人名": "流水市人民医院_安某某",
                    "content": [
                        "姓名：安某某      性别：女      年龄：99岁      民族：汉族      婚姻状况：丧偶      职业：退休教师      住址：流水市茉莉街62号",
                        "居留地：流水市茉莉街62号"
                    ]
                }
            ],
            "答案": "根据霜叶市第一人民医院的住院病历，喻某某的住址是霜叶市雨燕街84号；根据流水市人民医院的住院病历，安某某的住址是流水市茉莉街62号。"
        },
        {
            "问题类型": "多文档信息整合问题",
            "问题": "根据霜叶市第一人民医院和流水市人民医院的住院病历，喻某某和安某某的主诉分别是什么？",
            "ref": [
                {
                    "医院_病人名": "霜叶市第一人民医院_喻某某",
                    "content": [
                        "主诉：",
                        "贫血、体力下降、腹部突出2个月余"
                    ]
                },
                {
                    "医院_病人名": "流水市人民医院_安某某",
                    "content": [
                        "主诉：",
                        "晨僵伴多关节疼痛1年，加重3月。"
                    ]
                }
            ],
            "答案": "根据霜叶市第一人民医院的住院病历，喻某某的主诉是贫血、体力下降、腹部突出2个月余；根据流水市人民医院的住院病历，安某某的主诉是晨僵伴多关节疼痛1年，加重3月。"
        },
        {
            "问题类型": "多文档信息整合问题",
            "问题": "根据霜叶市第一人民医院和流水市人民医院的住院病历，喻某某和安某某的初步诊断分别是什么？",
            "ref": [
                {
                    "医院_病人名": "霜叶市第一人民医院_喻某某",
                    "content": [
                        "初步诊断：",
                        "地中海贫血"
                    ]
                },
                {
                    "医院_病人名": "流水市人民医院_安某某",
                    "content": [
                        "初步诊断：",
                        "类风湿性关节炎"
                    ]
                }
            ],
            "答案": "根据霜叶市第一人民医院的住院病历，喻某某的初步诊断是地中海贫血；根据流水市人民医院的住院病历，安某某的初步诊断是类风湿性关节炎。"
        },
        {
            "问题类型": "多文档信息整合问题",
            "问题": "根据霜叶市第一人民医院和流水市人民医院的住院病历，喻某某和安某某的伴随症状分别是什么？",
            "ref": [
                {
                    "医院_病人名": "霜叶市第一人民医院_喻某某",
                    "content": [
                        "伴有轻度头晕、心悸和乏力，需要休息时仍能缓解。"
                    ]
                },
                {
                    "医院_病人名": "流水市人民医院_安某某",
                    "content": [
                        "伴随症状：伴有关节疲乏、乏力，偶有低热，但无明显发热。"
                    ]
                }
            ],
            "答案": "根据霜叶市第一人民医院的住院病历，喻某某的伴随症状是轻度头晕、心悸和乏力；根据流水市人民医院的住院病历，安某某的伴随症状是关节疲乏、乏力，偶有低热。"
        }
    ],
    "qa_multi_document_compare": [
        {
            "问题类型": "多文档时间序列问题",
            "问题": "根据霜叶市第一人民医院和流水市人民医院的住院病历，喻某某和安某某的入院时间谁更早？",
            "ref": [
                {
                    "医院_病人名": "霜叶市第一人民医院_喻某某",
                    "content": [
                        "入院时间：2月4日"
                    ]
                },
                {
                    "医院_病人名": "流水市人民医院_安某某",
                    "content": [
                        "入院时间：8月28日      记录时间：8月28日      病史陈述者：本人"
                    ]
                }
            ],
            "答案": "根据霜叶市第一人民医院的住院病历，喻某某的入院时间是2月4日；根据流水市人民医院的住院病历，安某某的入院时间是8月28日。所以，喻某某的入院时间更早。"
        }
    ]
}