{
    "courtAndProcuratorate": {
        "court": "Danbury, Pinehurst, Court",
        "procuratorate": "Danbury, Pinehurst, Procuratorate"
    },
    "chiefJudge": "C. Ward",
    "judge": "G. Robinson",
    "clerk": "G. Morgan",
    "defendant": {
        "name": "P. Anderson",
        "gender": "male",
        "birthdate": "7th, April, 1965",
        "residence": "44, Foxboro street, Pinehurst",
        "ethnicity": "Caucasian",
        "occupation": "Senior Government Auditor"
    },
    "defenseLawyer": {
        "name": "J. Thomas",
        "lawFirm": "Hamilton & Associates Law Firm"
    },
    "caseProcess": [
        {
            "event": "Case Filing and Investigation",
            "date": "1st, March, 2023",
            "description": "The Danbury, Pinehurst, Procuratorate received a whistleblower's report alleging that P. Anderson had been accepting bribes and manipulating audits for personal gain. An investigation was officially launched."
        },
        {
            "event": "Detention Measures Taken",
            "date": "15th, March, 2023",
            "description": "Preliminary evidence deemed sufficient to warrant detention measures to prevent Anderson from tampering with investigation or fleeing the jurisdiction."
        },
        {
            "event": "Criminal Detention",
            "date": "17th, March, 2023",
            "description": "Anderson was detained under criminal suspicion of bending the law for personal gain and held at Pinehurst Detention Facility."
        },
        {
            "event": "Arrest",
            "date": "20th, March, 2023",
            "description": "Formal charges were filed and Anderson was arrested for the Crime of Bending the Law for Personal Gain, following the completion of the preliminary inquiry."
        }
    ],
    "criminalFacts": [
        {
            "crimeName": "Crime of Bending the Law for Personal Gain",
            "details": [
                {
                    "timePeriod": "January 2022 - February 2023",
                    "behavior": "P. Anderson, while occupying the position of Senior Government Auditor, repeatedly manipulated and altered audit reports in exchange for bribes from various entities.",
                    "evidence": [
                        "Sworn affidavit from the whistleblower",
                        "Bank statements showing multiple payments totaling $150,000 from the accounts of XYZ Construction Co. to Anderson's personal account between January 2022 and February 2023",
                        "Email communications between Anderson and XYZ Construction Co. coordinated the delivery of altered reports",
                        "Expert testimony confirming the authenticity of the altered reports"
                    ]
                },
                {
                    "timePeriod": "May 2022",
                    "behavior": "Accepted a $20,000 bribe from ABC Manufacturing to overlook serious infractions in their financial records.",
                    "evidence": [
                        "Bank transaction records confirming the $20,000 payment",
                        "Testimony from John Doe, CFO of ABC Manufacturing",
                        "Digital forensic analysis recovering deleted emails discussing the transaction"
                    ]
                },
                {
                    "timePeriod": "December 2022",
                    "behavior": "Intervened in an investigation of DEF Services, for a sum of $35,000, ensuring the company passed the audit without due scrutiny.",
                    "evidence": [
                        "Wire transfer records showing a payment of $35,000 to a foreign account linked to Anderson",
                        "Documentation recovered from DEF Services detailing the bribe",
                        "Witness testimony from a former employee of DEF Services who facilitated the payment"
                    ]
                },
                {
                    "timePeriod": "February 2023",
                    "behavior": "Manipulation of audit findings in favor of GHI Corporation after receiving $50,000 in cryptocurrency to a wallet owned by Anderson.",
                    "evidence": [
                        "Blockchain analysis tracing the $50,000 transaction to Anderson's digital wallet",
                        "Encrypted correspondence between Anderson and GHI Corporation's representative",
                        "Accounting documents from GHI Corporation showing discrepancies corrected post-payment"
                    ]
                }
            ]
        }
    ],
    "legalProcedure": {
        "judgmentDate": "30th, June, 2023",
        "judgmentResult": [
            {
                "crimeName": "Crime of Bending the Law for Personal Gain",
                "sentence": "5 years of imprisonment and a fine of $300,000",
                "sentencingConsiderations": "The court considered the significant financial harm caused, the undermining of public trust in the auditing process, and the level of premeditation in Anderson's actions, but also noted his lack of prior criminal record."
            }
        ]
    },
    "Generated Article": "**IN THE DANBURY, PINEHURST COURT**\n\n**CRIMINAL JUDGMENT**\n\n**Court: Danbury, Pinehurst Court**  \n**Procuratorate: Danbury, Pinehurst Procuratorate**  \n\n**Chief Judge: C. Ward**  \n**Judge: G. Robinson**  \n**Clerk: G. Morgan**\n\n**Defendant:**  \n**Name:** P. Anderson  \n**Gender:** Male  \n**Birthdate:** 7th April, 1965  \n**Residence:** 44 Foxboro Street, Pinehurst  \n**Ethnicity:** Caucasian  \n**Occupation:** Senior Government Auditor  \n\n**Defense Lawyer:**  \n**Name:** J. Thomas  \n**Law Firm:** Hamilton & Associates Law Firm  \n\n---\n\n**CASE PROCEDURES**  \nOn the 1st of March, 2023, the Danbury, Pinehurst Procuratorate received a whistleblower's report that alleged P. Anderson, who was then acting in his capacity as a Senior Government Auditor, had been accepting bribes and falsifying audit reports for personal gain. In response to the allegations, an investigation was launched to uncover the veracity of the claims.\n\nDuring the early days of March 2023, preliminary investigations gathered enough evidence to suspect Anderson of interference with the lawful audit processes. Consequently, on the 15th of March, 2023, it was determined that detention measures should be applied. This decision was predicated on the need to prevent Anderson from potentially tampering with crucial evidence or fleeing the jurisdiction. \n\nTwo days later, on the 17th of March, Anderson was formally detained at the Pinehurst Detention Facility under suspicions tied to the crime of bending the law for personal gain. The formal arrest followed on the 20th of March, upon the filing of official charges after the preliminary inquiry had been completed. It was at this juncture that the allegations against Anderson had been sufficiently substantiated to proceed to trial.\n\n---\n\n**CASE STATEMENT**  \nP. Anderson, holding the position of Senior Government Auditor, was entrusted with the vital responsibility of auditing financial records of various entities. However, from January 2022 up until February 2023, Anderson accepted a series of bribes and adjusted audit reports in favor of the bribing entities, thereby abusing his professional power for personal enrichment.\n\nThroughout the duration commencing January 2022 and culminating in February 2023, Anderson systematically manipulated audit reports following the receipt of pecuniary inducements. These actions were undeniably in violation of the ethical and legal parameters governing his profession.\n\nIn May 2022, Anderson agreed to obscure serious financial infractions within ABC Manufacturing's records, accepting a sum of $20,000 in return. This transactional arrangement was clandestinely discussed through digital correspondence and subsequently confirmed by bank transaction records.\n\nAn additional instance of corruption was evidenced in December 2022. Anderson accepted a bribe of $35,000 from DEF Services. His intervention ensured the company passed the audit without the due scrutiny that would have otherwise identified various compliance failures. Wire transfer records backed by documentation from DEF Services were critical in establishing the factuality of this transaction.\n\nFinally, in February 2023, Anderson engaged in fraudulent activities by altering audit findings for the benefit of GHI Corporation. In return, he received $50,000 in cryptocurrency. A meticulous blockchain analysis confirmed the placement of these funds into Anderson's digital wallet, corroborated by encrypted correspondences between Anderson and GHI Corporation’s representatives.\n\n---\n\n**CHARGE**  \nThe defendant, P. Anderson, stood accused of violating Article No. 397, specifically charged with the Crime of Bending the Law for Personal Gain.\n\n---\n\n**EVIDENCE DESCRIPTION**  \nThe prosecution presented an array of evidence, which collectively portrayed a consistent pattern of conduct amounting to the bending of the law for personal gain. This included:\n\n1. **Sworn Affidavit from the Whistleblower:** A critical component that initiated the probe into the defendant’s conduct.\n2. **Bank Statements:** Detailed records disclosed multiple payments summing $150,000 from various accounts of XYZ Construction Co. to Anderson’s personal account over the identified period.\n3. **Email Communications:** Numerous emails between Anderson and XYZ Construction Co. illustrated the methodical coordination of bribery arrangements.\n4. **Expert Testimony:** This testified to the authenticity of both the altered audit reports and the digital communications intercepted.\n5. **Transaction Records:** Banking records confirmed specific bribes, notably the transaction involving $20,000 from ABC Manufacturing and the wire transfer of $35,000 from DEF Services.\n6. **Witness Testimonies:** Testimonies from John Doe, the CFO of ABC Manufacturing, and a former employee of DEF Services, affirmed Anderson’s involvement in these corrupt undertakings.\n7. **Digital Forensic Analysis:** Recovered emails discussing bribes and containing encrypted exchanges revealed the sordid details of Anderson’s negotiations.\n8. **Blockchain Analysis:** This traced the cryptocurrency transaction of $50,000 to Anderson’s digital wallet, underpinning the financial underpinnings of his crimes.\n9. **Accounting Documents:** Discrepancies noted in financial records of GHI Corporation were synchronized with the timeframe of the received payments.\n\n---\n\n**SENTENCING CONSIDERATIONS**  \nIn reaching its judgment, this court reexamined the significant financial harm caused by the defendant's actions. Anderson's deeds not only inflicted considerable economic damage but also markedly undermined public trust in the integrity of the auditing process. \n\nFurther, the calculated and premeditated nature of the conduct demonstrated a conscious disregard for ethical standards and legal obligations. The court, however, took into account that Anderson had no prior criminal record, which signified a non-recurring breach of conduct rather than habitual criminal behavior.\n\n---\n\n**JUDGMENT RESULT**  \nHaving thoroughly examined the aforementioned evidence and considerations, this court finds P. Anderson guilty of the Crime of Bending the Law for Personal Gain under Article No. 397.\n\nThis court hereby sentences P. Anderson to five years of imprisonment and imposes a fine of $300,000. The severity of the penalty reflects both the entrenched breach of trust placed by the public in the auditing institution and the cumulative financial malfeasance engaged by the defendant.\n\n---\n\n**APPEAL RIGHTS EXPLANATION**  \nThe defendant, P. Anderson, reserves the right to file an appeal against this judgment. Such an appeal must comply with the procedural regulations stipulated in the Criminal Procedure Code. This should be filed within a statutory period following the date of this judgment being rendered. Should Anderson or his defense counsel desire to challenge this court’s findings, they are advised to do so by following the formal channels of appellate review. This ensures that any grievances concerning this judgment are addressed within the bounds of the judicial framework.\n\n**Judgment rendered on this 30th day of June, 2023.**  \n\n**G. Morgan**  \n**Court Clerk, Danbury, Pinehurst Court**\n\nReference Article is below：\nArticle 397\nState organ personnel who abuse their power or neglect their duties, causing significant losses to public property, the state, and people's interests, shall be sentenced to fixed-term imprisonment of not more than three years or criminal detention; if the circumstances are particularly serious, they shall be sentenced to fixed-term imprisonment of more than three years but not more than seven years.",
    "qa_fact_based": [
        {
            "question type": "Factual Question",
            "question": "According to the court judgment of Danbury, Pinehurst, Court, what was P. Anderson's occupation?",
            "answer": "Senior Government Auditor.",
            "ref": [
                "**Occupation:** Senior Government Auditor"
            ]
        },
        {
            "question type": "Factual Question",
            "question": "According to the court judgment of Danbury, Pinehurst, Court, what was the total amount of bribes P. Anderson received from XYZ Construction Co.?",
            "answer": "$150,000.",
            "ref": [
                "2. **Bank Statements:** Detailed records disclosed multiple payments summing $150,000 from various accounts of XYZ Construction Co. to Anderson’s personal account over the identified period."
            ]
        },
        {
            "question type": "Factual Question",
            "question": "According to the court judgment of Danbury, Pinehurst, Court, who was the chief judge?",
            "answer": "C. Ward.",
            "ref": [
                "**Chief Judge: C. Ward**"
            ]
        },
        {
            "question type": "Factual Question",
            "question": "According to the court judgment of Danbury, Pinehurst, Court, what was the amount of the bribe P. Anderson received from DEF Services?",
            "answer": "$35,000.",
            "ref": [
                "Anderson accepted a bribe of $35,000 from DEF Services.",
                "5. **Transaction Records:** Banking records confirmed specific bribes, notably the transaction involving $20,000 from ABC Manufacturing and the wire transfer of $35,000 from DEF Services."
            ]
        }
    ],
    "qa_multi_hop": [
        {
            "question type": "Multi-hop Reasoning Question",
            "question": "According to the judgment of Danbury, Pinehurst, Court, how many instances of accepting bribes did P. Anderson commit in total?",
            "answer": "According to the judgment, P. Anderson committed a total of four instances of accepting bribes: from XYZ Construction Co., ABC Manufacturing, DEF Services, and GHI Corporation.",
            "ref": [
                "However, from January 2022 up until February 2023, Anderson accepted a series of bribes and adjusted audit reports in favor of the bribing entities, thereby abusing his professional power for personal enrichment.",
                "In May 2022, Anderson agreed to obscure serious financial infractions within ABC Manufacturing's records, accepting a sum of $20,000 in return.",
                "Anderson accepted a bribe of $35,000 from DEF Services.",
                "Finally, in February 2023, Anderson engaged in fraudulent activities by altering audit findings for the benefit of GHI Corporation.",
                "2. **Bank Statements:** Detailed records disclosed multiple payments summing $150,000 from various accounts of XYZ Construction Co. to Anderson’s personal account over the identified period."
            ]
        },
        {
            "question type": "Multi-hop Reasoning Question",
            "question": "According to the judgment of Danbury, Pinehurst, Court, what is the total amount of bribes received by P. Anderson in all his crimes?",
            "answer": "P. Anderson received $150,000 from XYZ Construction Co. between January 2022 and February 2023, $20,000 from ABC Manufacturing in May 2022, $35,000 from DEF Services in December 2022, and $50,000 from GHI Corporation in February 2023. The total amount is $150,000 + $20,000 + $35,000 + $50,000 = $255,000.",
            "ref": [
                "However, from January 2022 up until February 2023, Anderson accepted a series of bribes and adjusted audit reports in favor of the bribing entities, thereby abusing his professional power for personal enrichment.",
                "In May 2022, Anderson agreed to obscure serious financial infractions within ABC Manufacturing's records, accepting a sum of $20,000 in return.",
                "Anderson accepted a bribe of $35,000 from DEF Services.",
                "Finally, in February 2023, Anderson engaged in fraudulent activities by altering audit findings for the benefit of GHI Corporation.",
                "2. **Bank Statements:** Detailed records disclosed multiple payments summing $150,000 from various accounts of XYZ Construction Co. to Anderson’s personal account over the identified period.",
                "5. **Transaction Records:** Banking records confirmed specific bribes, notably the transaction involving $20,000 from ABC Manufacturing and the wire transfer of $35,000 from DEF Services.",
                "8. **Blockchain Analysis:** This traced the cryptocurrency transaction of $50,000 to Anderson’s digital wallet, underpinning the financial underpinnings of his crimes."
            ]
        },
        {
            "question type": "Multi-hop Reasoning Question",
            "question": "According to the judgment of Danbury, Pinehurst, Court, how many pieces of evidence were presented against P. Anderson in total?",
            "answer": "For XYZ Construction Co., there were 4 pieces of evidence: a sworn affidavit, bank statements, email communications, and expert testimony. For ABC Manufacturing, there were 3 pieces of evidence: bank transaction records, testimony from John Doe, and digital forensic analysis. For DEF Services, there were 3 pieces of evidence: wire transfer records, documentation from DEF Services, and witness testimony. For GHI Corporation, there were 3 pieces of evidence: blockchain analysis, encrypted correspondence, and accounting documents. The total number of pieces of evidence is 4 + 3 + 3 + 3 = 13.",
            "ref": [
                "1. **Sworn Affidavit from the Whistleblower:** A critical component that initiated the probe into the defendant’s conduct.",
                "2. **Bank Statements:** Detailed records disclosed multiple payments summing $150,000 from various accounts of XYZ Construction Co. to Anderson’s personal account over the identified period.",
                "3. **Email Communications:** Numerous emails between Anderson and XYZ Construction Co. illustrated the methodical coordination of bribery arrangements.",
                "4. **Expert Testimony:** This testified to the authenticity of both the altered audit reports and the digital communications intercepted.",
                "5. **Transaction Records:** Banking records confirmed specific bribes, notably the transaction involving $20,000 from ABC Manufacturing and the wire transfer of $35,000 from DEF Services.",
                "6. **Witness Testimonies:** Testimonies from John Doe, the CFO of ABC Manufacturing, and a former employee of DEF Services, affirmed Anderson’s involvement in these corrupt undertakings.",
                "7. **Digital Forensic Analysis:** Recovered emails discussing bribes and containing encrypted exchanges revealed the sordid details of Anderson’s negotiations.",
                "8. **Blockchain Analysis:** This traced the cryptocurrency transaction of $50,000 to Anderson’s digital wallet, underpinning the financial underpinnings of his crimes.",
                "9. **Accounting Documents:** Discrepancies noted in financial records of GHI Corporation were synchronized with the timeframe of the received payments."
            ]
        }
    ],
    "qa_summary": [
        {
            "question type": "Summarization Question",
            "question": "According to the judgment of Danbury, Pinehurst, Court, summarize the facts of P. Anderson's crimes.",
            "answer": "P. Anderson, while serving as a Senior Government Auditor, engaged in multiple instances of bending the law for personal gain. Between January 2022 and February 2023, he manipulated and altered audit reports in exchange for bribes. In May 2022, he accepted a $20,000 bribe from ABC Manufacturing to overlook financial infractions. In December 2022, he intervened in an investigation of DEF Services for a $35,000 bribe, ensuring the company passed the audit without scrutiny. In February 2023, he manipulated audit findings in favor of GHI Corporation after receiving $50,000 in cryptocurrency.",
            "ref": [
                "P. Anderson, holding the position of Senior Government Auditor, was entrusted with the vital responsibility of auditing financial records of various entities.",
                "However, from January 2022 up until February 2023, Anderson accepted a series of bribes and adjusted audit reports in favor of the bribing entities, thereby abusing his professional power for personal enrichment.",
                "Throughout the duration commencing January 2022 and culminating in February 2023, Anderson systematically manipulated audit reports following the receipt of pecuniary inducements.",
                "In May 2022, Anderson agreed to obscure serious financial infractions within ABC Manufacturing's records, accepting a sum of $20,000 in return.",
                "This transactional arrangement was clandestinely discussed through digital correspondence and subsequently confirmed by bank transaction records.",
                "An additional instance of corruption was evidenced in December 2022.",
                "Anderson accepted a bribe of $35,000 from DEF Services.",
                "His intervention ensured the company passed the audit without the due scrutiny that would have otherwise identified various compliance failures.",
                "Wire transfer records backed by documentation from DEF Services were critical in establishing the factuality of this transaction.",
                "Finally, in February 2023, Anderson engaged in fraudulent activities by altering audit findings for the benefit of GHI Corporation.",
                "In return, he received $50,000 in cryptocurrency.",
                "A meticulous blockchain analysis confirmed the placement of these funds into Anderson's digital wallet, corroborated by encrypted correspondences between Anderson and GHI Corporation’s representatives."
            ]
        },
        {
            "question type": "Summarization Question",
            "question": "According to the judgment of Danbury, Pinehurst, Court, summarize the evidence of P. Anderson's crimes.",
            "answer": "The evidence against P. Anderson includes a sworn affidavit from the whistleblower, bank statements showing multiple payments summing $150,000 from various accounts of XYZ Construction Co. to Anderson's personal account, email communications coordinating the delivery of altered reports, expert testimony confirming the authenticity of the altered reports, bank transaction records confirming a $20,000 payment from ABC Manufacturing, testimony from John Doe, CFO of ABC Manufacturing, digital forensic analysis recovering deleted emails discussing the transaction, wire transfer records showing a $35,000 payment to a foreign account linked to Anderson, documentation from DEF Services detailing the bribe, witness testimony from a former employee of DEF Services, blockchain analysis tracing a $50,000 transaction to Anderson's digital wallet, encrypted correspondence between Anderson and GHI Corporation’s representative, and accounting documents from GHI Corporation showing discrepancies corrected post-payment.",
            "ref": [
                "1. **Sworn Affidavit from the Whistleblower:** A critical component that initiated the probe into the defendant’s conduct.",
                "2. **Bank Statements:** Detailed records disclosed multiple payments summing $150,000 from various accounts of XYZ Construction Co. to Anderson’s personal account over the identified period.",
                "3. **Email Communications:** Numerous emails between Anderson and XYZ Construction Co. illustrated the methodical coordination of bribery arrangements.",
                "4. **Expert Testimony:** This testified to the authenticity of both the altered audit reports and the digital communications intercepted.",
                "5. **Transaction Records:** Banking records confirmed specific bribes, notably the transaction involving $20,000 from ABC Manufacturing and the wire transfer of $35,000 from DEF Services.",
                "6. **Witness Testimonies:** Testimonies from John Doe, the CFO of ABC Manufacturing, and a former employee of DEF Services, affirmed Anderson’s involvement in these corrupt undertakings.",
                "7. **Digital Forensic Analysis:** Recovered emails discussing bribes and containing encrypted exchanges revealed the sordid details of Anderson’s negotiations.",
                "8. **Blockchain Analysis:** This traced the cryptocurrency transaction of $50,000 to Anderson’s digital wallet, underpinning the financial underpinnings of his crimes.",
                "9. **Accounting Documents:** Discrepancies noted in financial records of GHI Corporation were synchronized with the timeframe of the received payments."
            ]
        },
        {
            "question type": "Summarization Question",
            "question": "According to the judgment of Danbury, Pinehurst, Court, summarize the case process of P. Anderson.",
            "answer": "The case process began on 1st March 2023 when the Danbury, Pinehurst, Procuratorate received a whistleblower's report alleging that P. Anderson had been accepting bribes and manipulating audits for personal gain, leading to an official investigation. On 15th March 2023, preliminary evidence warranted detention measures to prevent Anderson from tampering with the investigation or fleeing. Anderson was detained on 17th March 2023 under criminal suspicion of bending the law for personal gain and held at Pinehurst Detention Facility. Formal charges were filed, and Anderson was arrested on 20th March 2023 for the Crime of Bending the Law for Personal Gain following the completion of the preliminary inquiry.",
            "ref": [
                "On the 1st of March, 2023, the Danbury, Pinehurst Procuratorate received a whistleblower's report that alleged P. Anderson, who was then acting in his capacity as a Senior Government Auditor, had been accepting bribes and falsifying audit reports for personal gain.",
                "In response to the allegations, an investigation was launched to uncover the veracity of the claims.",
                "During the early days of March 2023, preliminary investigations gathered enough evidence to suspect Anderson of interference with the lawful audit processes.",
                "Consequently, on the 15th of March, 2023, it was determined that detention measures should be applied.",
                "This decision was predicated on the need to prevent Anderson from potentially tampering with crucial evidence or fleeing the jurisdiction.",
                "Two days later, on the 17th of March, Anderson was formally detained at the Pinehurst Detention Facility under suspicions tied to the crime of bending the law for personal gain.",
                "The formal arrest followed on the 20th of March, upon the filing of official charges after the preliminary inquiry had been completed.",
                "It was at this juncture that the allegations against Anderson had been sufficiently substantiated to proceed to trial."
            ]
        },
        {
            "question type": "Summarization Question",
            "question": "According to the judgment of Danbury, Pinehurst, Court, summarize the judgment result for P. Anderson.",
            "answer": "P. Anderson was found guilty of the Crime of Bending the Law for Personal Gain and was sentenced to 5 years of imprisonment and a fine of $300,000. The court considered the significant financial harm caused, the undermining of public trust in the auditing process, and the level of premeditation in Anderson's actions, but also noted his lack of prior criminal record.",
            "ref": [
                "Having thoroughly examined the aforementioned evidence and considerations, this court finds P. Anderson guilty of the Crime of Bending the Law for Personal Gain under Article No. 397.",
                "This court hereby sentences P. Anderson to five years of imprisonment and imposes a fine of $300,000.",
                "The severity of the penalty reflects both the entrenched breach of trust placed by the public in the auditing institution and the cumulative financial malfeasance engaged by the defendant.",
                "In reaching its judgment, this court reexamined the significant financial harm caused by the defendant's actions.",
                "Anderson's deeds not only inflicted considerable economic damage but also markedly undermined public trust in the integrity of the auditing process.",
                "Further, the calculated and premeditated nature of the conduct demonstrated a conscious disregard for ethical standards and legal obligations.",
                "The court, however, took into account that Anderson had no prior criminal record, which signified a non-recurring breach of conduct rather than habitual criminal behavior."
            ]
        }
    ]
}